{"ongoing_trials": {}, "hyperparameters": {"space": [{"class_name": "Choice", "config": {"name": "batch_size", "default": 16, "conditions": [], "values": [16, 32, 64], "ordered": true}}, {"class_name": "Int", "config": {"name": "conv1_filters", "default": null, "conditions": [], "min_value": 16, "max_value": 64, "step": 16, "sampling": "linear"}}, {"class_name": "Int", "config": {"name": "conv2_filters", "default": null, "conditions": [], "min_value": 32, "max_value": 128, "step": 32, "sampling": "linear"}}, {"class_name": "Int", "config": {"name": "conv3_filters", "default": null, "conditions": [], "min_value": 64, "max_value": 256, "step": 64, "sampling": "linear"}}, {"class_name": "Int", "config": {"name": "dense_units", "default": null, "conditions": [], "min_value": 64, "max_value": 256, "step": 64, "sampling": "linear"}}, {"class_name": "Float", "config": {"name": "dropout_rate", "default": 0.2, "conditions": [], "min_value": 0.2, "max_value": 0.5, "step": 0.1, "sampling": "linear"}}, {"class_name": "Float", "config": {"name": "learning_rate", "default": 0.0001, "conditions": [], "min_value": 0.0001, "max_value": 0.01, "step": null, "sampling": "log"}}], "values": {"batch_size": 16, "conv1_filters": 16, "conv2_filters": 32, "conv3_filters": 64, "dense_units": 64, "dropout_rate": 0.2, "learning_rate": 0.0001}}, "start_order": ["00", "01", "02", "03", "04", "05", "06", "07", "08", "09"], "end_order": ["00", "01", "02", "03", "04", "05", "06", "07", "08", "09"], "run_times": {"00": 1, "01": 1, "02": 1, "03": 1, "04": 1, "05": 1, "06": 1, "07": 1, "08": 1, "09": 1}, "retry_queue": [], "seed": 5019, "seed_state": 5089, "tried_so_far": ["edd933a79bfa0eaf53333908085a872f", "9de324d63602d9537360535c62341634", "c4ba21bc8f04d93cd80188d30f8863b9", "06cde0483fe89aee1cc72f5456d166f7", "d65d713ac0815e2200f77b5b2b8851d1", "00fb27b434ac7bfe172b545af931ca70", "14c2c1cc156a0cbbc68d86070402f6ed", "85b94b7755e8b91287d478a53fec619c", "4753e9944777f894424612bcad78bc42", "59154236c0a96542af7d18da8e09d822"], "id_to_hash": {"00": "85b94b7755e8b91287d478a53fec619c", "01": "4753e9944777f894424612bcad78bc42", "02": "9de324d63602d9537360535c62341634", "03": "06cde0483fe89aee1cc72f5456d166f7", "04": "c4ba21bc8f04d93cd80188d30f8863b9", "05": "edd933a79bfa0eaf53333908085a872f", "06": "00fb27b434ac7bfe172b545af931ca70", "07": "14c2c1cc156a0cbbc68d86070402f6ed", "08": "59154236c0a96542af7d18da8e09d822", "09": "d65d713ac0815e2200f77b5b2b8851d1"}, "display": {"search_start": "2025-03-23T18:09:01.841216", "trial_start": {"00": "2025-03-23T18:09:01.841216", "01": "2025-03-23T18:11:26.869300", "02": "2025-03-23T18:12:35.102893", "03": "2025-03-23T18:14:11.779951", "04": "2025-03-23T18:15:12.690953", "05": "2025-03-23T18:16:25.969759", "06": "2025-03-23T18:17:39.175057", "07": "2025-03-23T18:20:03.400149", "08": "2025-03-23T18:21:28.082287", "09": "2025-03-23T18:22:50.276435"}, "trial_number": {"00": 1, "01": 2, "02": 3, "03": 4, "04": 5, "05": 6, "06": 7, "07": 8, "08": 9, "09": 10}}}